cloudformation_seed/__init__.py
cloudformation_seed/cfn_stack.py
cloudformation_seed/cfn_stackset.py
cloudformation_seed/cfn_template.py
cloudformation_seed/lambdas.py
cloudformation_seed/s3_classes.py
cloudformation_seed/stack_deployer.py
cloudformation_seed/util.py
cloudformation_seed/version.py
cloudformation_seed-1.3.6.dist-info/LICENSE.txt
cloudformation_seed-1.3.6.dist-info/METADATA
cloudformation_seed-1.3.6.dist-info/WHEEL
cloudformation_seed-1.3.6.dist-info/entry_points.txt
cloudformation_seed-1.3.6.dist-info/top_level.txt
cloudformation_seed-1.3.6.dist-info/RECORD
