Metadata-Version: 2.1
Name: cloudformation-seed
Version: 1.3.6
Summary: Orchestrates large Cloudformation deployments
Home-page: https://github.com/Innablr/cloudformation-seed
Author: Alex Bukharov
Author-email: alex.bukharov@innablr.com.au
License: MIT
Classifier: License :: OSI Approved :: MIT License
Classifier: Programming Language :: Python :: 3
Classifier: Programming Language :: Python :: 3.7
License-File: LICENSE.txt
Requires-Dist: boto3 (>=1.9.64)
Requires-Dist: PyYAML (>=5.1)
Requires-Dist: colorama (>=0.4.1)
Requires-Dist: objectpath (==0.6.1)
